build/lib/odahuflow/sdk/__init__.py
build/lib/odahuflow/sdk/config.py
build/lib/odahuflow/sdk/definitions.py
build/lib/odahuflow/sdk/io_proc_utils.py
build/lib/odahuflow/sdk/logger.py
build/lib/odahuflow/sdk/root_models.py
build/lib/odahuflow/sdk/utils.py
build/lib/odahuflow/sdk/version.py
build/lib/odahuflow/sdk/clients/__init__.py
build/lib/odahuflow/sdk/clients/api.py
build/lib/odahuflow/sdk/clients/api_aggregated.py
build/lib/odahuflow/sdk/clients/batch_job.py
build/lib/odahuflow/sdk/clients/batch_service.py
build/lib/odahuflow/sdk/clients/configuration.py
build/lib/odahuflow/sdk/clients/connection.py
build/lib/odahuflow/sdk/clients/deployment.py
build/lib/odahuflow/sdk/clients/feedback.py
build/lib/odahuflow/sdk/clients/model.py
build/lib/odahuflow/sdk/clients/oauth_handler.py
build/lib/odahuflow/sdk/clients/oidc.py
build/lib/odahuflow/sdk/clients/packaging.py
build/lib/odahuflow/sdk/clients/packaging_integration.py
build/lib/odahuflow/sdk/clients/route.py
build/lib/odahuflow/sdk/clients/templates.py
build/lib/odahuflow/sdk/clients/toolchain_integration.py
build/lib/odahuflow/sdk/clients/training.py
build/lib/odahuflow/sdk/clients/user_info.py
build/lib/odahuflow/sdk/containers/__init__.py
build/lib/odahuflow/sdk/containers/headers.py
build/lib/odahuflow/sdk/gppi/__init__.py
build/lib/odahuflow/sdk/gppi/entrypoint_invoke.py
build/lib/odahuflow/sdk/gppi/executor.py
build/lib/odahuflow/sdk/gppi/models.py
build/lib/odahuflow/sdk/local/__init__.py
build/lib/odahuflow/sdk/local/docker_utils.py
build/lib/odahuflow/sdk/local/packaging.py
build/lib/odahuflow/sdk/local/training.py
build/lib/odahuflow/sdk/models/__init__.py
build/lib/odahuflow/sdk/models/algorithm_source.py
build/lib/odahuflow/sdk/models/api_backend_config.py
build/lib/odahuflow/sdk/models/api_config.py
build/lib/odahuflow/sdk/models/api_local_backend_config.py
build/lib/odahuflow/sdk/models/auth_config.py
build/lib/odahuflow/sdk/models/base_model_.py
build/lib/odahuflow/sdk/models/batch_config.py
odahu_flow_sdk-1.6.1.dist-info/METADATA
odahu_flow_sdk-1.6.1.dist-info/WHEEL
odahu_flow_sdk-1.6.1.dist-info/top_level.txt
odahu_flow_sdk-1.6.1.dist-info/RECORD
