Metadata-Version: 2.1
Name: odahu-flow-sdk
Version: 1.6.1
Summary: Odahu-flow SDK
Home-page: https://github.com/odahu/odahu-flow
Author: Vlad Tokarev, Vitalik Solodilov
Author-email: vlad.tokarev.94@gmail.com, mcdkr@yandex.ru
License: Apache v2
Platform: UNKNOWN
Requires-Dist: requests (>=2.22.0)
Requires-Dist: urllib3 (>=1.24.3)
Requires-Dist: jinja2 (>=2.7.3)
Requires-Dist: pyyaml (>=3.1.2)
Requires-Dist: aiohttp (>=3.6.2)
Requires-Dist: pydantic (>=1.2)
Requires-Dist: dataclasses (>=0.6)
Requires-Dist: typing-extensions (>=3.6.5)
Requires-Dist: idna-ssl (>=1.1.0)
Requires-Dist: docker (>=4.2.0)
Requires-Dist: numpy (>=1.19.2)
